wsdottraffic/__init__.py
wsdottraffic/__main__.py
wsdottraffic/dicttools.py
wsdottraffic/fielddetection.py
wsdottraffic/jsonhelpers.py
wsdottraffic/parseutils.py
wsdottraffic/resturls.py
wsdottraffic/routeshields.py
wsdottraffic/gp/__init__.py
wsdottraffic/gp/__main__.py
wsdottraffic/gp/domains.json
wsdottraffic/gp/domaintools.py
wsdottraffic/gp/multipointtopoint.py
wsdottraffic/gp/tabledefs.json
wsdottraffic/gp/zipgdb.py
wsdottraffic/scanweb/__init__.py
wsdottraffic/scanweb/__main__.py
wsdottraffic/scanweb/gp/__init__.py
wsdottraffic/scanweb/gp/__main__.py
wsdottraffic-3.0.0.dist-info/DESCRIPTION.rst
wsdottraffic-3.0.0.dist-info/METADATA
wsdottraffic-3.0.0.dist-info/RECORD
wsdottraffic-3.0.0.dist-info/WHEEL
wsdottraffic-3.0.0.dist-info/entry_points.txt
wsdottraffic-3.0.0.dist-info/metadata.json
wsdottraffic-3.0.0.dist-info/top_level.txt
